LICENSE
MANIFEST.in
README.md
setup.cfg
setup.py
tests/__init__.py
tests/conftest.py
tests/test_all.py
tests/test_attr.py
tests/test_attrs.py
tests/test_bound_attr.py
tests/test_public_api.py
wr_attrs/__init__.py
wr_attrs/attrs3.py
wr_attrs.egg-info/PKG-INFO
wr_attrs.egg-info/SOURCES.txt
wr_attrs.egg-info/dependency_links.txt
wr_attrs.egg-info/top_level.txt