Metadata-Version: 1.1
Name: wr-attrs
Version: 3.3.1
Summary: wr-attrs
Home-page: https://github.com/jbasko/wr-attrs
Author: Jazeps Basko
Author-email: jazeps.basko@gmail.com
License: MIT
Platform: UNKNOWN
Classifier: Development Status :: 4 - Beta
Classifier: Intended Audience :: Developers
Classifier: Programming Language :: Python
Classifier: Programming Language :: Python :: 3
Classifier: Programming Language :: Python :: 3.5
Classifier: Programming Language :: Python :: 3.6
Classifier: License :: OSI Approved :: MIT License
